{"generator":"Code Snippets v3.3.0","date_created":"2023-04-25 14:41","snippets":[{"name":"Display product search on the shop page in WooCommerce","tags":["display","product","search","shop","woocommerce"],"scope":"global","code":"add_action( 'woocommerce_before_shop_loop', 'woocommerce_product_search_form' );\n\n\/**\n * Displays the product search form on the shop page.\n *\/\nfunction woocommerce_product_search_form() {\n    ?>\n    <form action=\"<?php echo esc_url( home_url( '\/' ) ); ?>\" method=\"get\">\n        <input type=\"text\" name=\"s\" value=\"<?php echo get_search_query(); ?>\" placeholder=\"<?php _e( 'Search for products&hellip;', 'woocommerce' ); ?>\" \/>\n        <input type=\"submit\" value=\"<?php _e( 'Search', 'woocommerce' ); ?>\" \/>\n\t    <input type=\"hidden\" name=\"post_type\" value=\"product\" \/>\n    <\/form>\n    <?php\n}","priority":"10"}]}