{"generator":"Code Snippets v2.14.1","date_created":"2021-04-07 20:34","snippets":[{"name":"Remove Users Endpoint in the WordPress REST API","desc":"https:\/\/wordpress.stackexchange.com\/questions\/252328\/wordpress-4-7-1-rest-api-still-exposing-users\nhttps:\/\/github.com\/WP-API\/WP-API\/issues\/2338","tags":["wordpress","rest","api","users"],"scope":"global","code":"add_filter( 'rest_endpoints', function( $endpoints ){\n    if ( isset( $endpoints['\/wp\/v2\/users'] ) ) {\n        unset( $endpoints['\/wp\/v2\/users'] );\n    }\n    if ( isset( $endpoints['\/wp\/v2\/users\/(?P<id>[\\d]+)'] ) ) {\n        unset( $endpoints['\/wp\/v2\/users\/(?P<id>[\\d]+)'] );\n    }\n    return $endpoints;\n});","priority":"10"}]}